.gitignore
README.txt
setup.py
collective/__init__.py
collective.pfg.sqladapter.egg-info/PKG-INFO
collective.pfg.sqladapter.egg-info/SOURCES.txt
collective.pfg.sqladapter.egg-info/dependency_links.txt
collective.pfg.sqladapter.egg-info/entry_points.txt
collective.pfg.sqladapter.egg-info/namespace_packages.txt
collective.pfg.sqladapter.egg-info/not-zip-safe
collective.pfg.sqladapter.egg-info/requires.txt
collective.pfg.sqladapter.egg-info/top_level.txt
collective/pfg/__init__.py
collective/pfg/sqladapter/__init__.py
collective/pfg/sqladapter/config.py
collective/pfg/sqladapter/configure.zcml
collective/pfg/sqladapter/handlers.py
collective/pfg/sqladapter/interfaces.py
collective/pfg/sqladapter/sqladapter.py
collective/pfg/sqladapter/testing.py
collective/pfg/sqladapter/profiles/default/factorytool.xml
collective/pfg/sqladapter/profiles/default/metadata.xml
collective/pfg/sqladapter/profiles/default/rolemap.xml
collective/pfg/sqladapter/profiles/default/types.xml
collective/pfg/sqladapter/profiles/default/workflows.xml
collective/pfg/sqladapter/profiles/default/types/FormFolder.xml
collective/pfg/sqladapter/profiles/default/types/SQLAdapter.xml
collective/pfg/sqladapter/tests/__init__.py
collective/pfg/sqladapter/tests/test_adapter.py
docs/HISTORY.txt
docs/LICENSE.GPL
docs/LICENSE.txt