Metadata-Version: 1.0
Name: collective.pfg.sqladapter
Version: 1.0
Summary: A PloneFormGen adapter that saves form input data in a SQL database
Home-page: https://github.com/4teamwork/collective.pfg.sqladapter
Author: Thomas Buchberger
Author-email: t.buchberger@4teamwork.ch
License: GPL
Platform: UNKNOWN
Classifier: Framework :: Plone
Classifier: Programming Language :: Python
